pmm/__init__.py
pmm/cli.py
pmm/config.py
pmm/data.py
pmm/utils.py
pmm-0.5.0.dist-info/DESCRIPTION.rst
pmm-0.5.0.dist-info/METADATA
pmm-0.5.0.dist-info/RECORD
pmm-0.5.0.dist-info/WHEEL
pmm-0.5.0.dist-info/entry_points.txt
pmm-0.5.0.dist-info/metadata.json
pmm-0.5.0.dist-info/top_level.txt
