Metadata-Version: 2.0
Name: pmm
Version: 0.5.0
Summary: PyPI Mirror and Index Server Manager
Home-page: https://github.com/wong2/pmm
Author: wong2
Author-email: wonderfuly@gmail.com
License: MIT
Keywords: pypi,mirror
Platform: UNKNOWN
Classifier: Development Status :: 4 - Beta
Classifier: Intended Audience :: Developers
Classifier: License :: OSI Approved :: MIT License
Classifier: Programming Language :: Python
Classifier: Programming Language :: Python :: 2.6
Classifier: Programming Language :: Python :: 2.7
Classifier: Programming Language :: Python :: 3.3
Classifier: Programming Language :: Python :: 3.4
Classifier: Programming Language :: Python :: 3.5
Requires-Dist: blindspin
Requires-Dist: configparser
Requires-Dist: crayons
Requires-Dist: pick
Requires-Dist: pip
Requires-Dist: requests
